{
  "agents": {
    "lead": {
      "persistent_name": "Keaton",
      "universe": "The Usual Suspects",
      "created_at": "2026-04-30T09:19:36Z",
      "legacy_named": false,
      "status": "active"
    },
    "frontend": {
      "persistent_name": "Hockney",
      "universe": "The Usual Suspects",
      "created_at": "2026-04-30T09:19:36Z",
      "legacy_named": false,
      "status": "active"
    },
    "backend": {
      "persistent_name": "Fenster",
      "universe": "The Usual Suspects",
      "created_at": "2026-04-30T09:19:36Z",
      "legacy_named": false,
      "status": "active"
    },
    "tester": {
      "persistent_name": "McManus",
      "universe": "The Usual Suspects",
      "created_at": "2026-04-30T09:19:36Z",
      "legacy_named": false,
      "status": "active"
    },
    "designer": {
      "persistent_name": "Verbal",
      "universe": "The Usual Suspects",
      "created_at": "2026-04-30T14:27:10Z",
      "legacy_named": false,
      "status": "active"
    },
    "product-manager": {
      "persistent_name": "Kobayashi",
      "universe": "The Usual Suspects",
      "created_at": "2026-04-30T14:27:10Z",
      "legacy_named": false,
      "status": "active"
    },
    "platform-sme": {
      "persistent_name": "Redfoot",
      "universe": "The Usual Suspects",
      "created_at": "2026-04-30T14:27:10Z",
      "legacy_named": false,
      "status": "active"
    }
  }
}
